pyocd_pemicro/__init__.py
pyocd_pemicro/_version.py
pyocd_pemicro/pemicro_probe.py
pyocd_pemicro-1.1.5.dist-info/LICENSE
pyocd_pemicro-1.1.5.dist-info/METADATA
pyocd_pemicro-1.1.5.dist-info/WHEEL
pyocd_pemicro-1.1.5.dist-info/entry_points.txt
pyocd_pemicro-1.1.5.dist-info/top_level.txt
pyocd_pemicro-1.1.5.dist-info/zip-safe
pyocd_pemicro-1.1.5.dist-info/RECORD
