Metadata-Version: 2.1
Name: pyocd-pemicro
Version: 1.1.5
Summary: PyOCD debug probe plugin for PEMicro debug probes
Home-page: https://github.com/pyocd/pyocd-pemicro
Download-URL: https://pypi.org/project/pyocd-pemicro/
Maintainer: Petr Gargulak, Chris Reed
Maintainer-email: petr.gargulak@nxp.com, chris.reed@arm.com
License: BSD-3-Clause
Project-URL: Documentation, https://pyocd.io/docs
Project-URL: Issues, https://github.com/pyocd/pyocd-pemicro/issues
Project-URL: Discussions, https://github.com/pyocd/pyOCD/discussions
Project-URL: Releases, https://github.com/pyocd/pyocd-pemicro/releases
Keywords: PEMicro PyPEMicro PyOCD Plugin
Platform: Windows
Platform: Linux
Platform: macOS
Platform: BSD
Classifier: Programming Language :: Python :: 3.7
Classifier: Programming Language :: Python :: 3.8
Classifier: Programming Language :: Python :: 3.9
Classifier: Programming Language :: Python :: 3.10
Classifier: Programming Language :: Python :: 3.11
Classifier: Operating System :: MacOS :: MacOS X
Classifier: Operating System :: Microsoft :: Windows
Classifier: Operating System :: POSIX :: Linux
Classifier: Operating System :: POSIX :: BSD
Classifier: License :: OSI Approved :: BSD License
Classifier: Topic :: Scientific/Engineering
Classifier: Topic :: Software Development
Classifier: Topic :: Software Development :: Debuggers
Classifier: Topic :: Software Development :: Embedded Systems
Classifier: Topic :: System :: Hardware
Classifier: Topic :: Utilities
Requires-Python: >=3.7.0
License-File: LICENSE
Requires-Dist: pypemicro (>=0.1.11)
